setup.cfg
setup.py
gwd/__init__.py
gwd.egg-info/PKG-INFO
gwd.egg-info/SOURCES.txt
gwd.egg-info/dependency_links.txt
gwd.egg-info/requires.txt
gwd.egg-info/top_level.txt