Metadata-Version: 1.0
Name: gwd
Version: 1.3.0
Summary: Global Watch Dog
Home-page: https://github.com/immesys/gwd-python
Author: Michael Andersen
Author-email: UNKNOWN
License: UNKNOWN
Platform: UNKNOWN
